<?xml version="1.0" encoding="UTF-8"?>
<document filename="us-040_2_0">
	<table id="1">
		<Coords points="92,442 92,528 350,528 350,442"/>
		<cell end-col="2" end-row="5" start-col="2" start-row="5">
			<Coords points="320,108,320,126,472,126,472,108"/>
			<content></content>
		</cell>
		<cell end-col="2" end-row="6" start-col="2" start-row="6">
			<Coords points="321,127,321,145,472,145,472,127"/>
			<content></content>
		</cell>
		<cell end-col="1" end-row="6" start-col="1" start-row="6">
			<Coords points="165,127,165,145,319,145,319,127"/>
			<content></content>
		</cell>
		<cell end-col="2" end-row="0" start-col="1" start-row="0">
			<Coords points="163,1,163,29,474,29,474,1"/>
			<content></content>
		</cell>
		<cell end-col="0" end-row="1" start-col="0" start-row="0">
			<Coords points="8,1,8,47,162,47,162,1"/>
			<content></content>
		</cell>
		<cell end-col="0" end-row="6" start-col="0" start-row="6">
			<Coords points="10,127,10,145,163,145,163,127"/>
			<content></content>
		</cell>
		<cell end-col="1" end-row="2" start-col="1" start-row="2">
			<Coords points="165,49,165,69,319,69,319,49"/>
			<content></content>
		</cell>
		<cell end-col="0" end-row="5" start-col="0" start-row="5">
			<Coords points="8,108,8,126,165,126,165,108"/>
			<content></content>
		</cell>
		<cell end-col="1" end-row="5" start-col="1" start-row="5">
			<Coords points="164,108,164,126,320,126,320,108"/>
			<content></content>
		</cell>
		<cell end-col="0" end-row="2" start-col="0" start-row="2">
			<Coords points="10,49,10,69,163,69,163,49"/>
			<content></content>
		</cell>
		<cell end-col="0" end-row="1" start-col="0" start-row="1">
			<Coords points="163,29,163,48,319,48,319,29"/>
			<content></content>
		</cell>
		<cell end-col="1" end-row="3" start-col="1" start-row="3">
			<Coords points="164,69,164,88,320,88,320,69"/>
			<content></content>
		</cell>
		<cell end-col="2" end-row="2" start-col="2" start-row="2">
			<Coords points="320,49,320,69,472,69,472,49"/>
			<content></content>
		</cell>
		<cell end-col="2" end-row="4" start-col="2" start-row="4">
			<Coords points="320,89,320,107,473,107,473,89"/>
			<content></content>
		</cell>
		<cell end-col="0" end-row="4" start-col="0" start-row="4">
			<Coords points="9,89,9,107,164,107,164,89"/>
			<content></content>
		</cell>
		<cell end-col="0" end-row="3" start-col="0" start-row="3">
			<Coords points="10,69,10,88,164,88,164,69"/>
			<content></content>
		</cell>
		<cell end-col="1" end-row="4" start-col="1" start-row="4">
			<Coords points="164,89,164,107,320,107,320,89"/>
			<content></content>
		</cell>
		<cell end-col="2" end-row="3" start-col="2" start-row="3">
			<Coords points="320,69,320,88,473,88,473,69"/>
			<content></content>
		</cell>
		<cell end-col="1" end-row="1" start-col="1" start-row="1">
			<Coords points="320,29,320,50,473,50,473,29"/>
			<content></content>
		</cell>
	</table>
</document>
